django_live_templates/__init__.py
django_live_templates/classes.py
django_live_templates/consumers.py
django_live_templates/models.py
django_live_templates/routing.py
django_live_templates/utils.py
django_live_templates/static/js/django_live_template.js
django_live_templates/templatetags/__init__.py
django_live_templates/templatetags/django_live_template.py
django_live_templates-0.1a0.dist-info/COPYING
django_live_templates-0.1a0.dist-info/METADATA
django_live_templates-0.1a0.dist-info/WHEEL
django_live_templates-0.1a0.dist-info/top_level.txt
django_live_templates-0.1a0.dist-info/RECORD
