Metadata-Version: 2.1
Name: django-live-templates
Version: 0.1a0
Summary: Django-Live-Templates is an extension to Django and Channels which adds support for live updating Django template snippets on model changes.
Home-page: https://github.com/mback2k/django-live-templates
Author: Marc Hoersken
Author-email: info@marc-hoersken.de
License: MIT
Platform: UNKNOWN
Classifier: Topic :: Internet :: WWW/HTTP :: Dynamic Content
Classifier: Intended Audience :: Developers
Classifier: License :: OSI Approved :: MIT License
Classifier: Programming Language :: Python
Classifier: Topic :: Software Development :: Libraries :: Python Modules
Classifier: Development Status :: 3 - Alpha
Classifier: Operating System :: OS Independent
Requires-Dist: channels (>=2.3.0)
Requires-Dist: django-redis (>=4.10.0)
